xcope_daemon/__init__.py
xcope_daemon/config.py
xcope_daemon/diagnose_daemon.py
xcope_daemon/diagnose_daemon_pb2.py
xcope_daemon/diagnose_daemon_pb2_grpc.py
xcope_daemon/docker_utils.py
xcope_daemon-0.0.3.dist-info/METADATA
xcope_daemon-0.0.3.dist-info/WHEEL
xcope_daemon-0.0.3.dist-info/top_level.txt
xcope_daemon-0.0.3.dist-info/RECORD
