Metadata-Version: 2.1
Name: xcope-daemon
Version: 0.0.3
Summary: Xcope diagnose daemon sdk. 
Home-page: https://github.com/pypa/sampleproject
Author: rwecho
Author-email: rwecho@live.com
Classifier: Programming Language :: Python :: 3
Classifier: License :: OSI Approved :: MIT License
Classifier: Operating System :: OS Independent
Requires-Python: >=3.6
Requires-Dist: grpcio (==1.51.1)
Requires-Dist: protobuf (==4.22.1)
